[
  {
    "name": "技术",
    "children": [
      {
        "name": "后端开发",
        "children": [
          {
            "name": "区块链工程师"
          },
          {
            "name": "Java"
          },
          {
            "name": "C/C++"
          },
          {
            "name": "PHP"
          },
          {
            "name": "C#"
          },
          {
            "name": ".NET"
          },
          {
            "name": "Python"
          },
          {
            "name": "Node.js"
          },
          {
            "name": "Golang"
          },
          {
            "name": "语音/视频/图形开发"
          },
          {
            "name": "全栈工程师"
          },
          {
            "name": "GIS工程师"
          },
          {
            "name": "其他后端开发"
          }
        ]
      },
      {
        "name": "前端/移动开发",
        "children": [
          {
            "name": "技术美术"
          },
          {
            "name": "鸿蒙开发工程师"
          },
          {
            "name": "Android"
          },
          {
            "name": "iOS"
          },
          {
            "name": "JavaScript"
          },
          {
            "name": "U3D"
          },
          {
            "name": "Cocos"
          },
          {
            "name": "UE4"
          },
          {
            "name": "前端开发工程师"
          }
        ]
      },
      {
        "name": "测试",
        "children": [
          {
            "name": "测试工程师"
          },
          {
            "name": "自动化测试"
          },
          {
            "name": "功能测试"
          },
          {
            "name": "性能测试"
          },
          {
            "name": "测试开发"
          },
          {
            "name": "游戏测试"
          },
          {
            "name": "硬件测试"
          },
          {
            "name": "软件测试"
          },
          {
            "name": "渗透测试"
          },
          {
            "name": "测试经理"
          }
        ]
      },
      {
        "name": "运维/技术支持",
        "children": [
          {
            "name": "技术文档工程师"
          },
          {
            "name": "运维工程师"
          },
          {
            "name": "运维开发工程师"
          },
          {
            "name": "网络工程师"
          },
          {
            "name": "系统工程师"
          },
          {
            "name": "IT技术支持"
          },
          {
            "name": "系统管理员"
          },
          {
            "name": "网络安全"
          },
          {
            "name": "系统安全"
          },
          {
            "name": "DBA"
          }
        ]
      },
      {
        "name": "数据",
        "children": [
          {
            "name": "爬虫工程师"
          },
          {
            "name": "数据治理"
          },
          {
            "name": "数据采集"
          },
          {
            "name": "ETL工程师"
          },
          {
            "name": "数据仓库"
          },
          {
            "name": "数据开发"
          },
          {
            "name": "数据分析师"
          },
          {
            "name": "数据架构师"
          }
        ]
      },
      {
        "name": "项目管理",
        "children": [
          {
            "name": "软件项目经理"
          },
          {
            "name": "项目经理/主管"
          },
          {
            "name": "实施顾问"
          },
          {
            "name": "实施工程师"
          },
          {
            "name": "硬件项目经理"
          }
        ]
      },
      {
        "name": "电子/硬件开发",
        "children": [
          {
            "name": "光学工程师"
          },
          {
            "name": "电源工程师"
          },
          {
            "name": "电声工程师"
          },
          {
            "name": "电子维修技术员"
          },
          {
            "name": "电池工程师"
          },
          {
            "name": "硬件工程师"
          },
          {
            "name": "嵌入式软件工程师"
          },
          {
            "name": "单片机"
          },
          {
            "name": "电路设计"
          },
          {
            "name": "驱动开发工程师"
          },
          {
            "name": "系统集成"
          },
          {
            "name": "FPGA开发"
          },
          {
            "name": "DSP开发"
          },
          {
            "name": "PCB工程师"
          },
          {
            "name": "射频工程师"
          },
          {
            "name": "电子工程师"
          }
        ]
      },
      {
        "name": "通信",
        "children": [
          {
            "name": "通信技术工程师"
          },
          {
            "name": "通信研发工程师"
          },
          {
            "name": "数据通信工程师"
          },
          {
            "name": "宽带装维"
          },
          {
            "name": "有线传输工程师"
          },
          {
            "name": "无线/天线工程师"
          },
          {
            "name": "通信标准化工程师"
          },
          {
            "name": "通信项目专员"
          },
          {
            "name": "通信项目经理"
          },
          {
            "name": "核心网工程师"
          },
          {
            "name": "光网络工程师"
          }
        ]
      },
      {
        "name": "半导体/芯片",
        "children": [
          {
            "name": "模拟版图设计工程师"
          },
          {
            "name": "芯片测试工程师"
          },
          {
            "name": "DFT工程师"
          },
          {
            "name": "数字前端设计师"
          },
          {
            "name": "数字后端工程师"
          },
          {
            "name": "模拟IC设计工程师"
          },
          {
            "name": "集成电路IC设计"
          },
          {
            "name": "FAE"
          },
          {
            "name": "数字IC验证工程师"
          }
        ]
      },
      {
        "name": "高端技术职位",
        "children": [
          {
            "name": "技术经理"
          },
          {
            "name": "技术总监"
          },
          {
            "name": "架构师"
          },
          {
            "name": "CTO/CIO"
          },
          {
            "name": "运维总监"
          },
          {
            "name": "技术合伙人"
          }
        ]
      },
      {
        "name": "人工智能",
        "children": [
          {
            "name": "大模型算法"
          },
          {
            "name": "规控算法"
          },
          {
            "name": "SLAM算法"
          },
          {
            "name": "高性能计算工程师"
          },
          {
            "name": "数据挖掘"
          },
          {
            "name": "搜索算法"
          },
          {
            "name": "自然语言处理算法"
          },
          {
            "name": "推荐算法"
          },
          {
            "name": "算法工程师"
          },
          {
            "name": "自动驾驶系统工程师"
          },
          {
            "name": "风控算法"
          },
          {
            "name": "机器学习"
          },
          {
            "name": "深度学习"
          },
          {
            "name": "语音算法"
          },
          {
            "name": "图像算法"
          },
          {
            "name": "算法研究员"
          }
        ]
      },
      {
        "name": "销售技术支持",
        "children": [
          {
            "name": "销售技术支持"
          },
          {
            "name": "售前技术支持"
          },
          {
            "name": "售后技术支持"
          }
        ]
      },
      {
        "name": "其他技术职位",
        "children": [
          {
            "name": "其他技术职位"
          }
        ]
      }
    ]
  },
  {
    "name": "产品",
    "children": [
      {
        "name": "游戏策划/制作",
        "children": [
          {
            "name": "系统策划"
          },
          {
            "name": "游戏策划"
          },
          {
            "name": "游戏制作人"
          },
          {
            "name": "游戏数值策划"
          }
        ]
      },
      {
        "name": "产品经理",
        "children": [
          {
            "name": "AI产品经理"
          },
          {
            "name": "化妆品产品经理"
          },
          {
            "name": "需求分析工程师"
          },
          {
            "name": "产品经理"
          },
          {
            "name": "移动产品经理"
          },
          {
            "name": "数据产品经理"
          },
          {
            "name": "电商产品经理"
          },
          {
            "name": "产品专员/助理"
          },
          {
            "name": "硬件产品经理"
          },
          {
            "name": "产品总监"
          },
          {
            "name": "用户研究"
          }
        ]
      }
    ]
  },
  {
    "name": "设计",
    "children": [
      {
        "name": "视觉/交互设计",
        "children": [
          {
            "name": "视觉设计师"
          },
          {
            "name": "UI设计师"
          },
          {
            "name": "平面设计"
          },
          {
            "name": "3D设计师"
          },
          {
            "name": "原画师"
          },
          {
            "name": "美工"
          },
          {
            "name": "包装设计"
          },
          {
            "name": "设计师助理"
          },
          {
            "name": "动画设计"
          },
          {
            "name": "插画师"
          },
          {
            "name": "漫画师"
          },
          {
            "name": "修图师"
          },
          {
            "name": "UX/交互设计师"
          },
          {
            "name": "广告设计"
          }
        ]
      },
      {
        "name": "游戏设计",
        "children": [
          {
            "name": "游戏主美术"
          },
          {
            "name": "游戏特效"
          },
          {
            "name": "游戏UI设计"
          },
          {
            "name": "游戏场景"
          },
          {
            "name": "游戏角色"
          },
          {
            "name": "游戏动作"
          }
        ]
      },
      {
        "name": "设计管理",
        "children": [
          {
            "name": "设计总监/经理"
          },
          {
            "name": "视觉设计总监/经理"
          }
        ]
      },
      {
        "name": "非视觉设计",
        "children": [
          {
            "name": "家具拆单员"
          },
          {
            "name": "舞美设计师"
          },
          {
            "name": "鞋类设计师"
          },
          {
            "name": "CAD绘图员"
          },
          {
            "name": "展览/展示设计"
          },
          {
            "name": "照明设计"
          },
          {
            "name": "室内设计"
          },
          {
            "name": "软装设计师"
          },
          {
            "name": "服装/纺织设计"
          },
          {
            "name": "工业设计"
          },
          {
            "name": "家具设计"
          },
          {
            "name": "珠宝设计"
          },
          {
            "name": "陈列设计"
          }
        ]
      }
    ]
  },
  {
    "name": "客服/运营",
    "children": [
      {
        "name": "运营",
        "children": [
          {
            "name": "淘宝运营"
          },
          {
            "name": "天猫运营"
          },
          {
            "name": "京东运营"
          },
          {
            "name": "拼多多运营"
          },
          {
            "name": "亚马逊运营"
          },
          {
            "name": "阿里国际站运营"
          },
          {
            "name": "跨境电商产品开发"
          },
          {
            "name": "外卖运营"
          },
          {
            "name": "用户运营"
          },
          {
            "name": "产品运营"
          },
          {
            "name": "数据/策略运营"
          },
          {
            "name": "内容运营"
          },
          {
            "name": "商家运营"
          },
          {
            "name": "品类运营"
          },
          {
            "name": "游戏运营"
          },
          {
            "name": "网站运营"
          },
          {
            "name": "新媒体运营"
          },
          {
            "name": "社群运营"
          },
          {
            "name": "微信运营"
          },
          {
            "name": "线下拓展运营"
          },
          {
            "name": "国内电商运营"
          },
          {
            "name": "运营助理/专员"
          },
          {
            "name": "内容审核"
          },
          {
            "name": "数据标注/AI训练师"
          },
          {
            "name": "直播运营"
          },
          {
            "name": "跨境电商运营"
          },
          {
            "name": "视频运营"
          }
        ]
      },
      {
        "name": "客服",
        "children": [
          {
            "name": "售前客服"
          },
          {
            "name": "售后客服"
          },
          {
            "name": "网络客服"
          },
          {
            "name": "客服经理"
          },
          {
            "name": "客服专员"
          },
          {
            "name": "客服主管"
          },
          {
            "name": "电话客服"
          }
        ]
      },
      {
        "name": "高端运营职位",
        "children": [
          {
            "name": "运营总监"
          },
          {
            "name": "COO"
          },
          {
            "name": "客服总监"
          },
          {
            "name": "运营经理/主管"
          }
        ]
      },
      {
        "name": "其他运营职位",
        "children": [
          {
            "name": "其他运营职位"
          }
        ]
      }
    ]
  },
  {
    "name": "市场/公关/广告",
    "children": [
      {
        "name": "调研分析",
        "children": [
          {
            "name": "商业数据分析"
          },
          {
            "name": "选址开发"
          }
        ]
      },
      {
        "name": "政府事务",
        "children": [
          {
            "name": "社工"
          },
          {
            "name": "项目申报专员"
          },
          {
            "name": "政府关系"
          },
          {
            "name": "政策研究"
          }
        ]
      },
      {
        "name": "推广/投放",
        "children": [
          {
            "name": "信息流优化师"
          },
          {
            "name": "网络推广"
          },
          {
            "name": "市场推广/地推"
          },
          {
            "name": "SEO"
          },
          {
            "name": "SEM"
          },
          {
            "name": "游戏推广"
          },
          {
            "name": "媒介专员"
          },
          {
            "name": "媒介经理/总监"
          },
          {
            "name": "媒介投放"
          },
          {
            "name": "媒介商务BD"
          }
        ]
      },
      {
        "name": "市场营销",
        "children": [
          {
            "name": "市场营销策划"
          },
          {
            "name": "活动策划执行"
          },
          {
            "name": "海外市场"
          },
          {
            "name": "市场总监"
          },
          {
            "name": "CMO"
          },
          {
            "name": "会务/会展策划"
          },
          {
            "name": "会务/会展执行"
          }
        ]
      },
      {
        "name": "公关",
        "children": [
          {
            "name": "品牌公关"
          },
          {
            "name": "公关总监"
          }
        ]
      },
      {
        "name": "广告",
        "children": [
          {
            "name": "广告客户执行"
          },
          {
            "name": "创意总监"
          },
          {
            "name": "广告/会展项目经理"
          },
          {
            "name": "广告创意策划"
          },
          {
            "name": "美术指导"
          },
          {
            "name": "策划经理"
          },
          {
            "name": "广告文案"
          },
          {
            "name": "广告制作"
          },
          {
            "name": "广告审核"
          }
        ]
      },
      {
        "name": "其他市场职位",
        "children": [
          {
            "name": "其他市场职位"
          }
        ]
      }
    ]
  },
  {
    "name": "人力/财务/行政",
    "children": [
      {
        "name": "人力资源",
        "children": [
          {
            "name": "企业文化"
          },
          {
            "name": "招聘"
          },
          {
            "name": "HRBP"
          },
          {
            "name": "人力资源专员/助理"
          },
          {
            "name": "培训"
          },
          {
            "name": "薪酬绩效"
          },
          {
            "name": "人力资源经理/主管"
          },
          {
            "name": "人力资源总监"
          },
          {
            "name": "猎头顾问"
          },
          {
            "name": "员工关系"
          },
          {
            "name": "组织发展"
          }
        ]
      },
      {
        "name": "行政",
        "children": [
          {
            "name": "文员"
          },
          {
            "name": "档案管理"
          },
          {
            "name": "项目专员/助理"
          },
          {
            "name": "企业党建"
          },
          {
            "name": "行政专员/助理"
          },
          {
            "name": "前台"
          },
          {
            "name": "经理助理"
          },
          {
            "name": "后勤"
          },
          {
            "name": "行政经理/主管"
          },
          {
            "name": "行政总监"
          },
          {
            "name": "录入员"
          }
        ]
      },
      {
        "name": "财务",
        "children": [
          {
            "name": "建筑/工程会计"
          },
          {
            "name": "外勤会计"
          },
          {
            "name": "财务分析/财务BP"
          },
          {
            "name": "资金管理"
          },
          {
            "name": "会计"
          },
          {
            "name": "出纳"
          },
          {
            "name": "财务顾问"
          },
          {
            "name": "结算会计"
          },
          {
            "name": "税务"
          },
          {
            "name": "审计"
          },
          {
            "name": "成本会计"
          },
          {
            "name": "总账会计"
          },
          {
            "name": "财务经理/主管"
          },
          {
            "name": "CFO"
          },
          {
            "name": "财务总监/VP"
          }
        ]
      },
      {
        "name": "法务",
        "children": [
          {
            "name": "法务专员/助理"
          },
          {
            "name": "法律顾问"
          },
          {
            "name": "法务经理/主管"
          },
          {
            "name": "法务总监"
          }
        ]
      },
      {
        "name": "其他职能职位",
        "children": [
          {
            "name": "其他职能职位"
          }
        ]
      }
    ]
  },
  {
    "name": "高级管理",
    "children": [
      {
        "name": "高级管理职位",
        "children": [
          {
            "name": "高级管理职位"
          },
          {
            "name": "总裁/总经理/CEO"
          },
          {
            "name": "副总裁/副总经理/VP"
          },
          {
            "name": "分公司/代表处负责人"
          },
          {
            "name": "区域负责人(辖多个分公司)"
          },
          {
            "name": "总助/CEO助理/董事长助理"
          },
          {
            "name": "联合创始人"
          },
          {
            "name": "董事会秘书"
          }
        ]
      }
    ]
  },
  {
    "name": "销售",
    "children": [
      {
        "name": "销售行政/商务",
        "children": [
          {
            "name": "商务专员"
          },
          {
            "name": "客户成功"
          },
          {
            "name": "招商"
          },
          {
            "name": "业务跟单"
          },
          {
            "name": "商务经理"
          },
          {
            "name": "销售助理"
          },
          {
            "name": "商务总监"
          },
          {
            "name": "销售运营"
          }
        ]
      },
      {
        "name": "房地产销售/招商",
        "children": [
          {
            "name": "置业顾问"
          },
          {
            "name": "地产中介"
          },
          {
            "name": "地产招商"
          }
        ]
      },
      {
        "name": "服务业销售",
        "children": [
          {
            "name": "服装导购"
          },
          {
            "name": "家装导购"
          },
          {
            "name": "化妆品导购"
          },
          {
            "name": "会籍顾问"
          },
          {
            "name": "珠宝销售"
          },
          {
            "name": "旅游顾问"
          },
          {
            "name": "导购"
          }
        ]
      },
      {
        "name": "汽车销售",
        "children": [
          {
            "name": "汽车销售"
          },
          {
            "name": "汽车配件销售"
          }
        ]
      },
      {
        "name": "广告/会展销售",
        "children": [
          {
            "name": "广告销售"
          },
          {
            "name": "会议活动销售"
          },
          {
            "name": "会展活动销售"
          }
        ]
      },
      {
        "name": "金融销售",
        "children": [
          {
            "name": "机构业务经理"
          },
          {
            "name": "证券经纪人"
          },
          {
            "name": "信用卡销售"
          },
          {
            "name": "保险顾问"
          },
          {
            "name": "理财顾问"
          }
        ]
      },
      {
        "name": "外贸销售",
        "children": [
          {
            "name": "海外销售"
          },
          {
            "name": "外贸经理"
          },
          {
            "name": "外贸业务员"
          },
          {
            "name": "货代/物流销售"
          }
        ]
      },
      {
        "name": "销售",
        "children": [
          {
            "name": "销售专员"
          },
          {
            "name": "大客户代表"
          },
          {
            "name": "BD经理"
          },
          {
            "name": "渠道销售"
          },
          {
            "name": "电话销售"
          },
          {
            "name": "网络销售"
          },
          {
            "name": "销售工程师"
          },
          {
            "name": "客户经理"
          }
        ]
      },
      {
        "name": "教培销售",
        "children": [
          {
            "name": "课程顾问"
          },
          {
            "name": "留学顾问"
          }
        ]
      },
      {
        "name": "医疗销售",
        "children": [
          {
            "name": "口腔咨询师"
          },
          {
            "name": "医疗器械销售"
          },
          {
            "name": "医药代表"
          },
          {
            "name": "健康顾问"
          },
          {
            "name": "医美咨询"
          }
        ]
      },
      {
        "name": "销售管理",
        "children": [
          {
            "name": "销售经理/主管"
          },
          {
            "name": "销售总监"
          },
          {
            "name": "区域总监"
          },
          {
            "name": "城市经理"
          },
          {
            "name": "销售VP"
          }
        ]
      },
      {
        "name": "其他销售职位",
        "children": [
          {
            "name": "其他销售职位"
          }
        ]
      }
    ]
  },
  {
    "name": "直播/影视/传媒",
    "children": [
      {
        "name": "采编/写作/出版",
        "children": [
          {
            "name": "主编/副主编"
          },
          {
            "name": "文案编辑"
          },
          {
            "name": "网站编辑"
          },
          {
            "name": "印刷排版"
          },
          {
            "name": "记者/采编"
          },
          {
            "name": "编辑"
          },
          {
            "name": "作者/撰稿人"
          },
          {
            "name": "出版发行"
          }
        ]
      },
      {
        "name": "影视媒体",
        "children": [
          {
            "name": "带货主播"
          },
          {
            "name": "剧本杀主持人"
          },
          {
            "name": "剧本杀编剧"
          },
          {
            "name": "儿童引导师"
          },
          {
            "name": "游戏主播"
          },
          {
            "name": "模特"
          },
          {
            "name": "艺人助理"
          },
          {
            "name": "主持人/DJ"
          },
          {
            "name": "中控/场控/助播"
          },
          {
            "name": "灯光师"
          },
          {
            "name": "影视特效"
          },
          {
            "name": "导演/编导"
          },
          {
            "name": "摄影/摄像师"
          },
          {
            "name": "视频剪辑"
          },
          {
            "name": "音频编辑"
          },
          {
            "name": "经纪人/星探"
          },
          {
            "name": "后期制作"
          },
          {
            "name": "影视发行"
          },
          {
            "name": "影视策划"
          },
          {
            "name": "主播"
          },
          {
            "name": "演员/配音员"
          },
          {
            "name": "放映员"
          },
          {
            "name": "录音/音效"
          },
          {
            "name": "制片人"
          },
          {
            "name": "编剧"
          }
        ]
      },
      {
        "name": "其他传媒职位",
        "children": [
          {
            "name": "其他传媒职位"
          }
        ]
      }
    ]
  },
  {
    "name": "金融",
    "children": [
      {
        "name": "证券/基金/期货",
        "children": [
          {
            "name": "买方分析师"
          },
          {
            "name": "基金经理"
          },
          {
            "name": "投资银行业务"
          },
          {
            "name": "量化研究员"
          },
          {
            "name": "卖方分析师"
          },
          {
            "name": "证券交易员"
          }
        ]
      },
      {
        "name": "投融资",
        "children": [
          {
            "name": "投资者关系/证券事务代表"
          },
          {
            "name": "投资经理"
          },
          {
            "name": "行业研究"
          },
          {
            "name": "投资总监/VP"
          },
          {
            "name": "融资"
          },
          {
            "name": "并购"
          },
          {
            "name": "投后管理"
          },
          {
            "name": "投资助理"
          },
          {
            "name": "其他投融资职位"
          }
        ]
      },
      {
        "name": "银行",
        "children": [
          {
            "name": "柜员"
          },
          {
            "name": "客户经理"
          },
          {
            "name": "银行大堂经理"
          },
          {
            "name": "信贷专员"
          }
        ]
      },
      {
        "name": "保险",
        "children": [
          {
            "name": "保险精算师"
          },
          {
            "name": "保险理赔"
          }
        ]
      },
      {
        "name": "中后台",
        "children": [
          {
            "name": "风控"
          },
          {
            "name": "金融产品经理"
          },
          {
            "name": "资信评估"
          },
          {
            "name": "催收员"
          },
          {
            "name": "资产评估"
          },
          {
            "name": "合规稽查"
          },
          {
            "name": "清算"
          }
        ]
      },
      {
        "name": "其他金融职位",
        "children": [
          {
            "name": "其他金融职位"
          }
        ]
      }
    ]
  },
  {
    "name": "教育培训",
    "children": [
      {
        "name": "教育产品研发",
        "children": [
          {
            "name": "课程设计"
          },
          {
            "name": "课程编辑"
          },
          {
            "name": "培训研究"
          },
          {
            "name": "培训策划"
          }
        ]
      },
      {
        "name": "教育行政",
        "children": [
          {
            "name": "园长/副园长"
          },
          {
            "name": "校长/副校长"
          },
          {
            "name": "教务管理"
          },
          {
            "name": "教学管理"
          },
          {
            "name": "班主任/辅导员"
          },
          {
            "name": "就业老师"
          }
        ]
      },
      {
        "name": "教师",
        "children": [
          {
            "name": "地理教师"
          },
          {
            "name": "教师"
          },
          {
            "name": "感统训练教师"
          },
          {
            "name": "保育员"
          },
          {
            "name": "日语教师"
          },
          {
            "name": "其他外语教师"
          },
          {
            "name": "语文教师"
          },
          {
            "name": "数学教师"
          },
          {
            "name": "物理教师"
          },
          {
            "name": "化学教师"
          },
          {
            "name": "生物教师"
          },
          {
            "name": "家教"
          },
          {
            "name": "托管老师"
          },
          {
            "name": "早教老师"
          },
          {
            "name": "助教"
          },
          {
            "name": "高中教师"
          },
          {
            "name": "初中教师"
          },
          {
            "name": "小学教师"
          },
          {
            "name": "幼教"
          },
          {
            "name": "理科教师"
          },
          {
            "name": "文科教师"
          },
          {
            "name": "英语教师"
          }
        ]
      },
      {
        "name": "职业培训",
        "children": [
          {
            "name": "财会培训讲师"
          },
          {
            "name": "培训师"
          },
          {
            "name": "IT培训讲师"
          },
          {
            "name": "拓展培训"
          }
        ]
      },
      {
        "name": "特长培训",
        "children": [
          {
            "name": "少儿编程老师"
          },
          {
            "name": "乒乓球教练"
          },
          {
            "name": "羽毛球教练"
          },
          {
            "name": "足球教练"
          },
          {
            "name": "架子鼓老师"
          },
          {
            "name": "围棋老师"
          },
          {
            "name": "拳击教练"
          },
          {
            "name": "台球教练/助教"
          },
          {
            "name": "网球教练"
          },
          {
            "name": "普拉提老师"
          },
          {
            "name": "武术教练"
          },
          {
            "name": "轮滑教练"
          },
          {
            "name": "表演教师"
          },
          {
            "name": "机器人教师"
          },
          {
            "name": "书法教师"
          },
          {
            "name": "钢琴教师"
          },
          {
            "name": "吉他教师"
          },
          {
            "name": "古筝教师"
          },
          {
            "name": "播音主持教师"
          },
          {
            "name": "乐高教师"
          },
          {
            "name": "救生员"
          },
          {
            "name": "舞蹈老师"
          },
          {
            "name": "瑜伽老师"
          },
          {
            "name": "游泳教练"
          },
          {
            "name": "健身教练"
          },
          {
            "name": "篮球教练"
          },
          {
            "name": "跆拳道教练"
          },
          {
            "name": "音乐教师"
          },
          {
            "name": "美术教师"
          },
          {
            "name": "体育/体能老师"
          }
        ]
      },
      {
        "name": "其他教育培训职位",
        "children": [
          {
            "name": "其他教育培训职位"
          }
        ]
      }
    ]
  },
  {
    "name": "医疗健康",
    "children": [
      {
        "name": "临床试验",
        "children": [
          {
            "name": "临床监查员"
          },
          {
            "name": "临床医学经理/专员"
          },
          {
            "name": "临床协调员"
          },
          {
            "name": "临床数据分析"
          },
          {
            "name": "临床项目经理"
          },
          {
            "name": "临床医学总监"
          }
        ]
      },
      {
        "name": "医生/医技",
        "children": [
          {
            "name": "其他医生职位"
          },
          {
            "name": "幼儿园保健医"
          },
          {
            "name": "外科医生"
          },
          {
            "name": "儿科医生"
          },
          {
            "name": "妇产科医生"
          },
          {
            "name": "眼科医生"
          },
          {
            "name": "皮肤科医生"
          },
          {
            "name": "耳鼻喉科医生"
          },
          {
            "name": "麻醉科医生"
          },
          {
            "name": "病理科医生"
          },
          {
            "name": "医务管理"
          },
          {
            "name": "医疗机构院长"
          },
          {
            "name": "医生助理"
          },
          {
            "name": "放射科医生"
          },
          {
            "name": "超声科医生"
          },
          {
            "name": "内科医生"
          },
          {
            "name": "全科医生"
          },
          {
            "name": "中医"
          },
          {
            "name": "整形外科医生"
          },
          {
            "name": "精神心理科医生"
          },
          {
            "name": "药剂师"
          },
          {
            "name": "口腔科医生"
          },
          {
            "name": "验光师"
          },
          {
            "name": "医学检验"
          }
        ]
      },
      {
        "name": "护士/护理",
        "children": [
          {
            "name": "护士长"
          },
          {
            "name": "护士"
          },
          {
            "name": "导医"
          }
        ]
      },
      {
        "name": "理疗保健",
        "children": [
          {
            "name": "足疗师"
          },
          {
            "name": "按摩师"
          },
          {
            "name": "采耳师"
          },
          {
            "name": "产后康复师"
          },
          {
            "name": "营养师/健康管理师"
          },
          {
            "name": "理疗师"
          },
          {
            "name": "针灸推拿"
          },
          {
            "name": "康复治疗师"
          }
        ]
      },
      {
        "name": "生物医药",
        "children": [
          {
            "name": "细胞培养员"
          },
          {
            "name": "药物分析"
          },
          {
            "name": "药物合成"
          },
          {
            "name": "医疗产品技术支持"
          },
          {
            "name": "生物信息工程师"
          },
          {
            "name": "制剂研发"
          },
          {
            "name": "药理毒理研究员"
          },
          {
            "name": "生物学研究人员"
          },
          {
            "name": "药品注册"
          },
          {
            "name": "药品生产"
          },
          {
            "name": "医药项目经理"
          },
          {
            "name": "医药研发"
          }
        ]
      },
      {
        "name": "医疗器械",
        "children": [
          {
            "name": "试剂研发"
          },
          {
            "name": "医疗器械注册"
          },
          {
            "name": "医疗器械生产/质量管理"
          },
          {
            "name": "医疗器械研发"
          }
        ]
      },
      {
        "name": "药店",
        "children": [
          {
            "name": "药店店长"
          },
          {
            "name": "执业药师/驻店药师"
          },
          {
            "name": "药店店员"
          }
        ]
      },
      {
        "name": "其他医疗健康职位",
        "children": [
          {
            "name": "医学编辑"
          },
          {
            "name": "其他医疗健康职位"
          }
        ]
      }
    ]
  },
  {
    "name": "采购/贸易",
    "children": [
      {
        "name": "采购",
        "children": [
          {
            "name": "招标专员"
          },
          {
            "name": "投标专员"
          },
          {
            "name": "商品专员/助理"
          },
          {
            "name": "商品经理/主管"
          },
          {
            "name": "供应商质量工程师"
          },
          {
            "name": "采购总监"
          },
          {
            "name": "采购经理/主管"
          },
          {
            "name": "采购专员/助理"
          },
          {
            "name": "买手"
          },
          {
            "name": "采购工程师"
          }
        ]
      },
      {
        "name": "进出口贸易",
        "children": [
          {
            "name": "外贸跟单"
          },
          {
            "name": "报关/报检员"
          },
          {
            "name": "单证员"
          }
        ]
      }
    ]
  },
  {
    "name": "供应链/物流",
    "children": [
      {
        "name": "物流",
        "children": [
          {
            "name": "配送站长"
          },
          {
            "name": "跟车员"
          },
          {
            "name": "供应链专员"
          },
          {
            "name": "供应链经理"
          },
          {
            "name": "集装箱管理"
          },
          {
            "name": "物流专员"
          },
          {
            "name": "物流经理"
          },
          {
            "name": "物流运营"
          },
          {
            "name": "物流跟单"
          },
          {
            "name": "调度员"
          },
          {
            "name": "物流/仓储项目经理"
          },
          {
            "name": "水/空/陆运操作"
          }
        ]
      },
      {
        "name": "仓储",
        "children": [
          {
            "name": "仓库主管/经理"
          },
          {
            "name": "仓库管理员"
          },
          {
            "name": "仓库文员"
          },
          {
            "name": "配/理/拣/发货"
          }
        ]
      },
      {
        "name": "交通/运输",
        "children": [
          {
            "name": "无人机飞手"
          },
          {
            "name": "客运司机"
          },
          {
            "name": "商务司机"
          },
          {
            "name": "网约车司机"
          },
          {
            "name": "代驾司机"
          },
          {
            "name": "驾校教练"
          },
          {
            "name": "货运司机"
          },
          {
            "name": "配送员"
          },
          {
            "name": "快递员"
          },
          {
            "name": "送餐员"
          },
          {
            "name": "运输经理/主管"
          }
        ]
      },
      {
        "name": "高端供应链职位",
        "children": [
          {
            "name": "供应链总监"
          },
          {
            "name": "物流总监"
          }
        ]
      }
    ]
  },
  {
    "name": "房地产/建筑",
    "children": [
      {
        "name": "装饰装修",
        "children": [
          {
            "name": "装修造价"
          },
          {
            "name": "装修监理"
          },
          {
            "name": "装修项目经理"
          }
        ]
      },
      {
        "name": "工程管理",
        "children": [
          {
            "name": "工程检测员"
          },
          {
            "name": "成本工程师"
          },
          {
            "name": "工程招投标"
          },
          {
            "name": "工程监理"
          },
          {
            "name": "工程造价"
          },
          {
            "name": "资料员"
          },
          {
            "name": "建筑施工项目经理"
          },
          {
            "name": "施工员"
          },
          {
            "name": "测绘/测量"
          },
          {
            "name": "材料员"
          },
          {
            "name": "施工安全员"
          }
        ]
      },
      {
        "name": "建筑/装修工人",
        "children": [
          {
            "name": "水电工"
          },
          {
            "name": "泥瓦工"
          },
          {
            "name": "空调工"
          },
          {
            "name": "电梯工"
          }
        ]
      },
      {
        "name": "房地产规划开发",
        "children": [
          {
            "name": "房地产策划"
          },
          {
            "name": "房地产项目管理"
          },
          {
            "name": "房地产估价师"
          }
        ]
      },
      {
        "name": "建筑/规划设计",
        "children": [
          {
            "name": "建筑工程师"
          },
          {
            "name": "建筑设计师"
          },
          {
            "name": "土木/土建/结构工程师"
          },
          {
            "name": "园林/景观设计"
          },
          {
            "name": "城乡规划设计"
          },
          {
            "name": "弱电工程师"
          },
          {
            "name": "给排水工程师"
          },
          {
            "name": "暖通工程师"
          },
          {
            "name": "幕墙工程师"
          },
          {
            "name": "BIM工程师"
          },
          {
            "name": "建筑机电工程师"
          },
          {
            "name": "消防工程师"
          }
        ]
      },
      {
        "name": "物业管理",
        "children": [
          {
            "name": "物业工程主管"
          },
          {
            "name": "物业经理"
          },
          {
            "name": "综合维修工"
          },
          {
            "name": "绿化工"
          },
          {
            "name": "物业管理员"
          }
        ]
      },
      {
        "name": "其他房地产职位",
        "children": [
          {
            "name": "其他房地产职位"
          }
        ]
      }
    ]
  },
  {
    "name": "农/林/牧/渔",
    "children": [
      {
        "name": "农业/林业",
        "children": [
          {
            "name": "农业/林业技术员"
          }
        ]
      },
      {
        "name": "畜牧/渔业",
        "children": [
          {
            "name": "饲养员"
          },
          {
            "name": "养殖技术员"
          },
          {
            "name": "畜牧兽医"
          }
        ]
      }
    ]
  },
  {
    "name": "咨询/翻译/法律",
    "children": [
      {
        "name": "咨询/调研",
        "children": [
          {
            "name": "工程咨询"
          },
          {
            "name": "知识产权/专利/商标代理人"
          },
          {
            "name": "心理咨询师"
          },
          {
            "name": "婚恋咨询师"
          },
          {
            "name": "企业管理咨询"
          },
          {
            "name": "咨询总监"
          },
          {
            "name": "咨询经理"
          },
          {
            "name": "IT咨询顾问"
          },
          {
            "name": "人力资源咨询顾问"
          },
          {
            "name": "咨询项目管理"
          },
          {
            "name": "战略咨询"
          },
          {
            "name": "市场调研"
          }
        ]
      },
      {
        "name": "律师",
        "children": [
          {
            "name": "知识产权律师"
          },
          {
            "name": "律师助理"
          },
          {
            "name": "律师"
          }
        ]
      },
      {
        "name": "翻译",
        "children": [
          {
            "name": "英语翻译"
          },
          {
            "name": "日语翻译"
          },
          {
            "name": "韩语/朝鲜语翻译"
          },
          {
            "name": "法语翻译"
          },
          {
            "name": "德语翻译"
          },
          {
            "name": "俄语翻译"
          },
          {
            "name": "西班牙语翻译"
          },
          {
            "name": "其他语种翻译"
          }
        ]
      }
    ]
  },
  {
    "name": "旅游",
    "children": [
      {
        "name": "旅游服务",
        "children": [
          {
            "name": "计调"
          },
          {
            "name": "签证专员"
          },
          {
            "name": "导游"
          },
          {
            "name": "票务员"
          },
          {
            "name": "讲解员"
          },
          {
            "name": "旅游产品经理"
          }
        ]
      },
      {
        "name": "其他旅游职位",
        "children": [
          {
            "name": "其他旅游职位"
          }
        ]
      }
    ]
  },
  {
    "name": "服务业",
    "children": [
      {
        "name": "安保服务",
        "children": [
          {
            "name": "保安"
          },
          {
            "name": "安检员"
          },
          {
            "name": "保安主管/队长"
          },
          {
            "name": "押运员"
          },
          {
            "name": "消防中控员"
          },
          {
            "name": "消防维保员"
          }
        ]
      },
      {
        "name": "维修服务",
        "children": [
          {
            "name": "手机维修"
          },
          {
            "name": "家电维修"
          },
          {
            "name": "电动车/摩托车维修"
          },
          {
            "name": "电脑/打印机维修"
          }
        ]
      },
      {
        "name": "餐饮",
        "children": [
          {
            "name": "奶茶店店员"
          },
          {
            "name": "水台/水产员"
          },
          {
            "name": "面包/烘焙师"
          },
          {
            "name": "储备店长"
          },
          {
            "name": "调酒师"
          },
          {
            "name": "餐饮督导"
          },
          {
            "name": "后厨"
          },
          {
            "name": "配菜打荷"
          },
          {
            "name": "茶艺师"
          },
          {
            "name": "蛋糕/裱花师"
          },
          {
            "name": "餐饮学徒"
          },
          {
            "name": "面点师"
          },
          {
            "name": "行政总厨"
          },
          {
            "name": "厨师长"
          },
          {
            "name": "传菜员"
          },
          {
            "name": "洗碗工"
          },
          {
            "name": "凉菜厨师"
          },
          {
            "name": "中餐厨师"
          },
          {
            "name": "西餐厨师"
          },
          {
            "name": "日料厨师"
          },
          {
            "name": "烧烤师傅"
          },
          {
            "name": "收银"
          },
          {
            "name": "服务员"
          },
          {
            "name": "厨师"
          },
          {
            "name": "咖啡师"
          },
          {
            "name": "餐饮店长"
          },
          {
            "name": "餐饮前厅经理/领班"
          }
        ]
      },
      {
        "name": "酒店",
        "children": [
          {
            "name": "民宿管家"
          },
          {
            "name": "礼仪/迎宾/接待"
          },
          {
            "name": "酒店前厅经理"
          },
          {
            "name": "客房经理"
          },
          {
            "name": "酒店前台"
          },
          {
            "name": "客房服务员"
          },
          {
            "name": "酒店经理"
          }
        ]
      },
      {
        "name": "零售",
        "children": [
          {
            "name": "商场运营"
          },
          {
            "name": "督导/巡店"
          },
          {
            "name": "理货/陈列员"
          },
          {
            "name": "防损员"
          },
          {
            "name": "卖场经理"
          },
          {
            "name": "促销员"
          },
          {
            "name": "店员/营业员"
          },
          {
            "name": "门店店长"
          }
        ]
      },
      {
        "name": "美容美发",
        "children": [
          {
            "name": "纹绣师"
          },
          {
            "name": "美体师"
          },
          {
            "name": "美发助理/学徒"
          },
          {
            "name": "美容店长"
          },
          {
            "name": "美容顾问"
          },
          {
            "name": "发型师"
          },
          {
            "name": "美甲美睫师"
          },
          {
            "name": "化妆/造型/服装"
          },
          {
            "name": "养发师"
          },
          {
            "name": "美容导师"
          },
          {
            "name": "美容师"
          }
        ]
      },
      {
        "name": "汽车服务",
        "children": [
          {
            "name": "洗车工"
          },
          {
            "name": "加油员"
          },
          {
            "name": "汽车服务顾问"
          },
          {
            "name": "汽车维修"
          },
          {
            "name": "汽车美容"
          },
          {
            "name": "汽车查勘定损"
          },
          {
            "name": "二手车评估师"
          },
          {
            "name": "4S店店长/维修站长"
          },
          {
            "name": "汽车改装"
          }
        ]
      },
      {
        "name": "婚礼/花艺",
        "children": [
          {
            "name": "花艺师"
          },
          {
            "name": "婚礼策划"
          }
        ]
      },
      {
        "name": "宠物服务",
        "children": [
          {
            "name": "宠物美容"
          },
          {
            "name": "宠物医生"
          }
        ]
      },
      {
        "name": "家政/保洁",
        "children": [
          {
            "name": "保洁"
          },
          {
            "name": "保姆"
          },
          {
            "name": "月嫂"
          },
          {
            "name": "育婴师"
          },
          {
            "name": "护工"
          },
          {
            "name": "保洁主管"
          },
          {
            "name": "收纳师"
          }
        ]
      },
      {
        "name": "其他服务业职位",
        "children": [
          {
            "name": "网吧网管"
          },
          {
            "name": "游戏陪玩"
          },
          {
            "name": "其他服务业职位"
          }
        ]
      }
    ]
  },
  {
    "name": "生产制造",
    "children": [
      {
        "name": "电气/自动化",
        "children": [
          {
            "name": "电力工程师"
          },
          {
            "name": "自动化工程师"
          },
          {
            "name": "电气工程师"
          },
          {
            "name": "电气设计工程师"
          }
        ]
      },
      {
        "name": "环保",
        "children": [
          {
            "name": "环保工程师"
          },
          {
            "name": "环评工程师"
          },
          {
            "name": "EHS工程师"
          },
          {
            "name": "碳排放管理师"
          },
          {
            "name": "环境采样/检测员"
          }
        ]
      },
      {
        "name": "能源/地质",
        "children": [
          {
            "name": "地质工程师"
          },
          {
            "name": "光伏系统工程师"
          },
          {
            "name": "风电/光伏运维工程师"
          },
          {
            "name": "水利工程师"
          }
        ]
      },
      {
        "name": "生产营运",
        "children": [
          {
            "name": "厂务"
          },
          {
            "name": "厂长"
          },
          {
            "name": "生产总监"
          },
          {
            "name": "车间主任"
          },
          {
            "name": "生产组长/拉长"
          },
          {
            "name": "生产设备管理"
          },
          {
            "name": "生产计划/物料管理(PMC)"
          },
          {
            "name": "生产跟单/文员"
          }
        ]
      },
      {
        "name": "质量安全",
        "children": [
          {
            "name": "质检员"
          },
          {
            "name": "计量工程师"
          },
          {
            "name": "安全评价师"
          },
          {
            "name": "质量管理/测试工程师"
          },
          {
            "name": "可靠度工程师"
          },
          {
            "name": "失效分析工程师"
          },
          {
            "name": "产品认证工程师"
          },
          {
            "name": "体系工程师"
          },
          {
            "name": "体系审核员"
          },
          {
            "name": "生产安全员"
          },
          {
            "name": "汽车质量工程师"
          }
        ]
      },
      {
        "name": "汽车研发/制造",
        "children": [
          {
            "name": "总布置工程师"
          },
          {
            "name": "车身工程师"
          },
          {
            "name": "汽车工艺工程师"
          },
          {
            "name": "线束设计"
          },
          {
            "name": "汽车设计"
          },
          {
            "name": "汽车造型设计"
          },
          {
            "name": "底盘工程师"
          },
          {
            "name": "动力系统工程师"
          },
          {
            "name": "汽车电子工程师"
          },
          {
            "name": "汽车零部件设计"
          },
          {
            "name": "汽车项目管理"
          },
          {
            "name": "内外饰设计工程师"
          }
        ]
      },
      {
        "name": "机械设计/制造",
        "children": [
          {
            "name": "液压工程师"
          },
          {
            "name": "仿真工程师"
          },
          {
            "name": "装配工程师"
          },
          {
            "name": "家电/3C结构工程师"
          },
          {
            "name": "生产制造项目经理"
          },
          {
            "name": "电机工程师"
          },
          {
            "name": "热设计工程师"
          },
          {
            "name": "机械工程师"
          },
          {
            "name": "机械设备工程师"
          },
          {
            "name": "设备维修保养工程师"
          },
          {
            "name": "机械制图员"
          },
          {
            "name": "机械结构工程师"
          },
          {
            "name": "工业工程师(IE)"
          },
          {
            "name": "工艺工程师"
          },
          {
            "name": "材料工程师"
          },
          {
            "name": "机电工程师"
          },
          {
            "name": "冲压工程师"
          },
          {
            "name": "夹具工程师"
          },
          {
            "name": "模具工程师"
          },
          {
            "name": "焊接工程师"
          },
          {
            "name": "注塑工程师"
          },
          {
            "name": "铸造/锻造工程师"
          }
        ]
      },
      {
        "name": "化工",
        "children": [
          {
            "name": "化工项目经理"
          },
          {
            "name": "化工工程师"
          },
          {
            "name": "实验室技术员"
          },
          {
            "name": "涂料研发"
          },
          {
            "name": "化妆品研发"
          },
          {
            "name": "食品/饮料研发"
          }
        ]
      },
      {
        "name": "服装/纺织/皮革",
        "children": [
          {
            "name": "量体师"
          },
          {
            "name": "面料辅料开发"
          },
          {
            "name": "打样/制版"
          },
          {
            "name": "服装/纺织/皮革跟单"
          }
        ]
      },
      {
        "name": "技工/普工",
        "children": [
          {
            "name": "普工/操作工"
          },
          {
            "name": "挖掘机司机"
          },
          {
            "name": "弱电工"
          },
          {
            "name": "裁剪工"
          },
          {
            "name": "CNC数控操机/编程员"
          },
          {
            "name": "叉车工"
          },
          {
            "name": "铲车司机"
          },
          {
            "name": "焊工"
          },
          {
            "name": "氩弧焊工"
          },
          {
            "name": "电工"
          },
          {
            "name": "木工"
          },
          {
            "name": "油漆工"
          },
          {
            "name": "车工"
          },
          {
            "name": "磨工"
          },
          {
            "name": "铣工"
          },
          {
            "name": "钳工"
          },
          {
            "name": "钻工"
          },
          {
            "name": "铆工"
          },
          {
            "name": "钣金工"
          },
          {
            "name": "抛光工"
          },
          {
            "name": "机修工"
          },
          {
            "name": "折弯工"
          },
          {
            "name": "电镀工"
          },
          {
            "name": "喷塑工"
          },
          {
            "name": "注塑工"
          },
          {
            "name": "组装工"
          },
          {
            "name": "包装工"
          },
          {
            "name": "锅炉工"
          },
          {
            "name": "学徒工"
          },
          {
            "name": "缝纫工"
          },
          {
            "name": "搬运工/装卸工"
          },
          {
            "name": "切割工"
          },
          {
            "name": "样衣工"
          },
          {
            "name": "模具工"
          }
        ]
      },
      {
        "name": "其他生产制造职位",
        "children": [
          {
            "name": "其他生产制造职位"
          }
        ]
      }
    ]
  },
  {
    "name": "其他",
    "children": [
      {
        "name": "其他职位类别",
        "children": [
          {
            "name": "其他职位"
          }
        ]
      }
    ]
  }
]